tests
urlmatch
