Metadata-Version: 1.1
Name: urlmatch
Version: 1.0.1
Summary: Python library for matching URLs.
Home-page: https://github.com/jessepollak/urlmatch
Author: Jesse Pollak
Author-email: jpollak92@gmail.com
License: UNKNOWN
Platform: UNKNOWN
Classifier: License :: OSI Approved :: Apache Software License
Classifier: Operating System :: OS Independent
Classifier: Programming Language :: Python
